{"assets/docx/template.docx":["assets/docx/template.docx"],"assets/icon/add_company.gif":["assets/icon/add_company.gif"],"assets/icon/add_company_will.svg":["assets/icon/add_company_will.svg"],"assets/icon/add_technician.gif":["assets/icon/add_technician.gif"],"assets/icon/add_user_will.png":["assets/icon/add_user_will.png"],"assets/icon/add_user_will.png.svg":["assets/icon/add_user_will.png.svg"],"assets/icon/add_user_will.svg":["assets/icon/add_user_will.svg"],"assets/icon/icon.png":["assets/icon/icon.png"],"assets/icon/mxotechicon.png":["assets/icon/mxotechicon.png"],"assets/icon/path10.png":["assets/icon/path10.png"],"assets/images/.DS_Store":["assets/images/.DS_Store"],"assets/images/3dDownArrow.gif":["assets/images/3dDownArrow.gif"],"assets/images/acct_manager_gif.gif":["assets/images/acct_manager_gif.gif"],"assets/images/acct_manager_white.gif":["assets/images/acct_manager_white.gif"],"assets/images/avatar.png":["assets/images/avatar.png"],"assets/images/mobileFrame.png":["assets/images/mobileFrame.png"],"assets/images/mobileFrame2.png":["assets/images/mobileFrame2.png"],"assets/images/time-tracking.svg":["assets/images/time-tracking.svg"],"packages/cupertino_icons/assets/CupertinoIcons.ttf":["packages/cupertino_icons/assets/CupertinoIcons.ttf"],"packages/font_awesome_flutter/lib/fonts/fa-brands-400.ttf":["packages/font_awesome_flutter/lib/fonts/fa-brands-400.ttf"],"packages/font_awesome_flutter/lib/fonts/fa-regular-400.ttf":["packages/font_awesome_flutter/lib/fonts/fa-regular-400.ttf"],"packages/font_awesome_flutter/lib/fonts/fa-solid-900.ttf":["packages/font_awesome_flutter/lib/fonts/fa-solid-900.ttf"]}